[
  {
    "nickname": "Iconfont",
    "site": "https://www.iconfont.cn/",
    "content": "阿里巴巴矢量图标库，提供矢量图标下载、在线存储、格式转换等功能"
  },
  {
    "nickname": "Font Awesome",
    "site": "https://fa5.dashgame.com/#/%E5%9B%BE%E6%A0%87",
    "content": "一个基于CSS 和 LESS 的字体和图标工具包"
  },
  {
    "nickname": "Flaticon",
    "site": "https://www.flaticon.com/",
    "content": "海量扁平化免费的图标库"
  },
  {
    "nickname": "icons8",
    "site": "https://icons8.com/",
    "content": "独特系统平台风格和web图标库，下载免费图标，音乐"
  },
  {
    "nickname": "Unsplash",
    "site": "https://unsplash.com/",
    "content": "质量超高的免费图片素材库，无需注册，直接下载"
  },
  {
    "nickname": "Mixkit",
    "site": "https://mixkit.co/",
    "content": "免费、高质量、可商用的视频素材分享网站"
  },
  {
    "nickname": "WebGradients",
    "site": "https://webgradients.com/",
    "content": "渐变色搭配方案"
  },
  {
    "nickname": "CoolHue2.0",
    "site": "https://webkul.github.io/coolhue/",
    "content": "渐变色搭配方案"
  },
  {
    "nickname": "Gradient",
    "site": "https://gradient.shapefactory.co/?a=540A43&b=629EA1&d=25",
    "content": "渐变色搭配方案"
  },
  {
    "nickname": "UiGradients",
    "site": "https://uigradients.com/#JShine",
    "content": "渐变色搭配方案"
  }
]
